odoo/addons/sale_promotion/README.rst
odoo/addons/sale_promotion/__init__.py
odoo/addons/sale_promotion/__manifest__.py
odoo/addons/sale_promotion/i18n/ca_ES.po
odoo/addons/sale_promotion/i18n/es.po
odoo/addons/sale_promotion/models/__init__.py
odoo/addons/sale_promotion/models/product_campaign.py
odoo/addons/sale_promotion/models/product_campaign_item.py
odoo/addons/sale_promotion/models/sale_campaign.py
odoo/addons/sale_promotion/models/sale_order.py
odoo/addons/sale_promotion/models/sale_order_line.py
odoo/addons/sale_promotion/readme/CONFIGURE.md
odoo/addons/sale_promotion/readme/CONTRIBUTORS.md
odoo/addons/sale_promotion/readme/DESCRIPTION.md
odoo/addons/sale_promotion/readme/USAGE.md
odoo/addons/sale_promotion/security/ir.model.access.csv
odoo/addons/sale_promotion/static/description/icon.png
odoo/addons/sale_promotion/static/description/index.html
odoo/addons/sale_promotion/tests/__init__.py
odoo/addons/sale_promotion/tests/test_sale_promotion.py
odoo/addons/sale_promotion/views/product_campaign_views.xml
odoo/addons/sale_promotion/views/sale_campaign_views.xml
odoo/addons/sale_promotion/views/sale_order_views.xml
odoo_addon_sale_promotion-17.0.1.1.0.dist-info/METADATA
odoo_addon_sale_promotion-17.0.1.1.0.dist-info/WHEEL
odoo_addon_sale_promotion-17.0.1.1.0.dist-info/top_level.txt
odoo_addon_sale_promotion-17.0.1.1.0.dist-info/RECORD
